zevercloud/__init__.py
zevercloud/cloud.py
zevercloud/event.py
zevercloud/py.typed
zevercloud_api-0.2.1.dist-info/LICENSE
zevercloud_api-0.2.1.dist-info/METADATA
zevercloud_api-0.2.1.dist-info/WHEEL
zevercloud_api-0.2.1.dist-info/top_level.txt
zevercloud_api-0.2.1.dist-info/zip-safe
zevercloud_api-0.2.1.dist-info/RECORD
